sqlalchemy_imageattach_boto3.py
sqlalchemy_imageattach_boto3-0.1.1.dist-info/LICENSE
sqlalchemy_imageattach_boto3-0.1.1.dist-info/WHEEL
sqlalchemy_imageattach_boto3-0.1.1.dist-info/METADATA
sqlalchemy_imageattach_boto3-0.1.1.dist-info/RECORD
